clip2latent/data.py
clip2latent/latent_prior.py
clip2latent/models.py
clip2latent/train_utils.py
clip2latent/stylegan3/Dockerfile
clip2latent/stylegan3/LICENSE.txt
clip2latent/stylegan3/README.md
clip2latent/stylegan3/avg_spectra.py
clip2latent/stylegan3/calc_metrics.py
clip2latent/stylegan3/dataset_tool.py
clip2latent/stylegan3/environment.yml
clip2latent/stylegan3/gen_images.py
clip2latent/stylegan3/gen_video.py
clip2latent/stylegan3/legacy.py
clip2latent/stylegan3/train.py
clip2latent/stylegan3/visualizer.py
clip2latent/stylegan3/dnnlib/__init__.py
clip2latent/stylegan3/dnnlib/util.py
clip2latent/stylegan3/docs/avg_spectra_screen0.png
clip2latent/stylegan3/docs/avg_spectra_screen0_half.png
clip2latent/stylegan3/docs/configs.md
clip2latent/stylegan3/docs/dataset-tool-help.txt
clip2latent/stylegan3/docs/stylegan3-teaser-1920x1006.png
clip2latent/stylegan3/docs/train-help.txt
clip2latent/stylegan3/docs/troubleshooting.md
clip2latent/stylegan3/docs/visualizer_screen0.png
clip2latent/stylegan3/docs/visualizer_screen0_half.png
clip2latent/stylegan3/gui_utils/__init__.py
clip2latent/stylegan3/gui_utils/gl_utils.py
clip2latent/stylegan3/gui_utils/glfw_window.py
clip2latent/stylegan3/gui_utils/imgui_utils.py
clip2latent/stylegan3/gui_utils/imgui_window.py
clip2latent/stylegan3/gui_utils/text_utils.py
clip2latent/stylegan3/metrics/__init__.py
clip2latent/stylegan3/metrics/equivariance.py
clip2latent/stylegan3/metrics/frechet_inception_distance.py
clip2latent/stylegan3/metrics/inception_score.py
clip2latent/stylegan3/metrics/kernel_inception_distance.py
clip2latent/stylegan3/metrics/metric_main.py
clip2latent/stylegan3/metrics/metric_utils.py
clip2latent/stylegan3/metrics/perceptual_path_length.py
clip2latent/stylegan3/metrics/precision_recall.py
clip2latent/stylegan3/torch_utils/__init__.py
clip2latent/stylegan3/torch_utils/custom_ops.py
clip2latent/stylegan3/torch_utils/misc.py
clip2latent/stylegan3/torch_utils/persistence.py
clip2latent-1.0.dist-info/LICENSE.md
clip2latent-1.0.dist-info/METADATA
clip2latent-1.0.dist-info/WHEEL
clip2latent-1.0.dist-info/top_level.txt
clip2latent-1.0.dist-info/RECORD
