Metadata-Version: 2.1
Name: clip2latent
Version: 1.0
Summary: Official code for clip2latent
Author: Justin Pinkney
License-File: LICENSE.md
